{
  "node": {
    "70244e6c80d5cf6222086921177bb6c49ea0dd878d": {
      "workers": {
        "app/(dashboard)/liquidaciones/[id]/page": {
          "moduleId": 50687,
          "async": false,
          "exportedName": "saveAdelanto",
          "filename": "src/app/(dashboard)/liquidaciones/actions.ts"
        }
      },
      "layer": {
        "app/(dashboard)/liquidaciones/[id]/page": "action-browser"
      },
      "exportedName": "saveAdelanto",
      "filename": "src/app/(dashboard)/liquidaciones/actions.ts"
    },
    "40ef25f9283deeb572777fe9e1938a5bc6d1538b66": {
      "workers": {
        "app/(dashboard)/liquidaciones/[id]/page": {
          "moduleId": 50687,
          "async": false,
          "exportedName": "generarLiquidacion",
          "filename": "src/app/(dashboard)/liquidaciones/actions.ts"
        }
      },
      "layer": {
        "app/(dashboard)/liquidaciones/[id]/page": "action-browser"
      },
      "exportedName": "generarLiquidacion",
      "filename": "src/app/(dashboard)/liquidaciones/actions.ts"
    }
  },
  "edge": {}
}