{
  "/login/page": "app/login/page.js",
  "/(dashboard)/page": "app/(dashboard)/page.js",
  "/(dashboard)/movimientos/page": "app/(dashboard)/movimientos/page.js",
  "/(dashboard)/asistentes/page": "app/(dashboard)/asistentes/page.js",
  "/(dashboard)/socios/page": "app/(dashboard)/socios/page.js",
  "/(dashboard)/egresos/page": "app/(dashboard)/egresos/page.js",
  "/(dashboard)/cuentas/page": "app/(dashboard)/cuentas/page.js",
  "/(dashboard)/liquidaciones/page": "app/(dashboard)/liquidaciones/page.js",
  "/(dashboard)/asistentes/[id]/page": "app/(dashboard)/asistentes/[id]/page.js"
}